{
  "last_updated": "2025-12-04T13:38:50.741Z",
  "items": [
    {
      "ts": "2025-12-04T13:25:00.000Z",
      "headline": "Americans&#x2019; affordability crisis isn&#x2019;t tariffs&#x2019; fault &#x2014; it&#x2019;s something much, much deeper",
      "url": "https://www.marketwatch.com/story/americans-affordability-crisis-isnt-tariffs-fault-its-something-much-much-deeper-9b74ccfb?mod=mw_rss_topstories",
      "impact": "Bearish",
      "confidence": 3,
      "affected": [
        "COST"
      ],
      "summary_en": "Costs for the &#x201c;Unaffordability Five&#x201d; &#x2014; housing, food, healthcare, child care and energy &#x2014; were rising long before Trump&#x2019;s trade war.",
      "next_en": "Next: watch scheduled data (CPI/Jobs/Fed) or company guidance."
    },
    {
      "ts": "2025-12-04T12:47:00.000Z",
      "headline": "Dollar General sees more customer traffic at stores, something its top rival didn&#x2019;t have",
      "url": "https://www.marketwatch.com/story/dollar-general-sees-more-customer-traffic-at-stores-something-its-top-rival-didnt-have-c1956d45?mod=mw_rss_topstories",
      "impact": "Bullish",
      "confidence": 3,
      "affected": [
        "ED"
      ],
      "summary_en": "Dollar General&#x2019;s stock rallies as sales rose more than expected and the company took market share from its rivals.",
      "next_en": "Next: watch scheduled data (CPI/Jobs/Fed) or company guidance."
    },
    {
      "ts": "2025-12-04T13:19:00.000Z",
      "headline": "Strategist who nailed stocks, bonds and oil this year warns of &#x2018;optimism shakeout&#x2019; in early 2026",
      "url": "https://www.marketwatch.com/story/strategist-who-nailed-stocks-bonds-and-oil-this-year-warns-of-optimism-shakeout-in-early-2026-fcde8107?mod=mw_rss_topstories",
      "impact": "Neutral",
      "confidence": 2,
      "affected": [
        "NEE",
        "ED"
      ],
      "summary_en": "Look for more AI adoption to help broaden the stock market next year, but overly optimistic sentiment may need a reset early on, says strategist Warren Pies.",
      "next_en": "Next: watch scheduled data (CPI/Jobs/Fed) or company guidance."
    },
    {
      "ts": "2025-12-04T13:15:00.000Z",
      "headline": "AI can help many things &#x2014; but it can&#x2019;t fix bad CEOs and their money mistakes",
      "url": "https://www.marketwatch.com/story/ai-can-help-many-things-but-it-cant-fix-bad-ceos-and-their-money-mistakes-9bc2b3bc?mod=mw_rss_topstories",
      "impact": "Neutral",
      "confidence": 2,
      "affected": [
        "ED"
      ],
      "summary_en": "Job layoffs are being pinned on AI &#x2014; when poor leadership is really to blame.",
      "next_en": "Next: watch scheduled data (CPI/Jobs/Fed) or company guidance."
    },
    {
      "ts": "2025-12-04T12:50:00.000Z",
      "headline": "Market forecasts are usually wrong &#x2014; but this inflation-fighting investment can see the future",
      "url": "https://www.marketwatch.com/story/market-forecasts-are-usually-wrong-but-this-inflation-fighting-investment-can-see-the-future-f54efd7f?mod=mw_rss_topstories",
      "impact": "Neutral",
      "confidence": 3,
      "affected": [
        "ED"
      ],
      "summary_en": "&#x2018;It&#x2019;s tough to make predictions, especially about the future,&#x2019; Yogi Berra said. He could have been talking about Wall Street.",
      "next_en": "Next: watch scheduled data (CPI/Jobs/Fed) or company guidance."
    },
    {
      "ts": "2025-12-04T12:42:00.000Z",
      "headline": "When it comes to manufacturing billionaires, nobody does it better than the U.S.",
      "url": "https://www.marketwatch.com/story/when-it-comes-to-manufacturing-billionaires-nobody-does-it-better-than-the-u-s-eedbabed?mod=mw_rss_topstories",
      "impact": "Neutral",
      "confidence": 2,
      "affected": [
        "ED"
      ],
      "summary_en": "Confirming the great wealth transfer&#x2019;s acceleration, UBS says multigenerational billionaires inherited the largest amount in its report&#x2019;s history.",
      "next_en": "Next: watch scheduled data (CPI/Jobs/Fed) or company guidance."
    },
    {
      "ts": "2025-12-04T10:55:00.000Z",
      "headline": "Meta&#x2019;s accused of violating European antitrust rules. What the dispute is all about.",
      "url": "https://www.marketwatch.com/story/metas-accused-of-violating-european-antitrust-rules-what-the-dispute-is-all-about-1b24f096?mod=mw_rss_topstories",
      "impact": "Bearish",
      "confidence": 3,
      "affected": [
        "META",
        "ED"
      ],
      "summary_en": "The European Commission on Thursday accused Meta Platforms of violating antitrust rules, in the latest salvo by European regulators against American technology firms.",
      "next_en": "Next: watch scheduled data (CPI/Jobs/Fed) or company guidance."
    },
    {
      "ts": "2025-12-04T10:54:00.000Z",
      "headline": "&#x2018;She&#x2019;s young enough to be his granddaughter&#x2019;: My dad, 85, is being seduced by his caregiver. What can I do?",
      "url": "https://www.marketwatch.com/story/shes-young-enough-to-be-his-granddaughter-my-dad-85-is-being-seduced-by-his-caregiver-what-can-i-do-939fbec1?mod=mw_rss_topstories",
      "impact": "Neutral",
      "confidence": 2,
      "affected": [
        "ED"
      ],
      "summary_en": "&#x201c;He is of sound mind, but he might succumb to someone who offers him companionship.&#x201d;",
      "next_en": "Next: watch scheduled data (CPI/Jobs/Fed) or company guidance."
    },
    {
      "ts": "2025-12-04T10:54:00.000Z",
      "headline": "&#x2018;I love my work&#x2019;: I&#x2019;m a 61-year-old Chicago public-school teacher with a $60K annual pension. Is it safe?",
      "url": "https://www.marketwatch.com/story/i-love-my-work-im-a-61-year-old-public-school-teacher-and-have-a-60k-pension-is-it-safe-80461e5c?mod=mw_rss_topstories",
      "impact": "Neutral",
      "confidence": 2,
      "affected": [
        "INDEX/SECTOR"
      ],
      "summary_en": "&#x201c;I am aware that my pension as a Chicago public school teacher is dependent on factors that are very much in flux right now.&#x201d;",
      "next_en": "Next: watch scheduled data (CPI/Jobs/Fed) or company guidance."
    },
    {
      "ts": "2025-12-04T10:44:00.000Z",
      "headline": "Bitcoin could reach $170,000 if it trades like gold, says JPMorgan strategist",
      "url": "https://www.marketwatch.com/story/bitcoin-could-reach-170-000-if-it-trades-like-gold-says-jpmorgan-strategist-962b90a7?mod=mw_rss_topstories",
      "impact": "Neutral",
      "confidence": 2,
      "affected": [
        "INDEX/SECTOR"
      ],
      "summary_en": "Bitcoin could trade as high as $170,000 if investors were to value it like gold, according to a JPMorgan strategist.",
      "next_en": "Next: watch scheduled data (CPI/Jobs/Fed) or company guidance."
    },
    {
      "ts": "2025-12-03T16:00:00.000Z",
      "headline": "Federal Reserve Board issues enforcement action with former employee of First Financial Bank",
      "url": "https://www.federalreserve.gov/newsevents/pressreleases/enforcement20251203a.htm",
      "impact": "Neutral",
      "confidence": 2,
      "affected": [
        "ED"
      ],
      "summary_en": "Federal Reserve Board issues enforcement action with former employee of First Financial Bank",
      "next_en": "Next: watch scheduled data (CPI/Jobs/Fed) or company guidance."
    }
  ]
}